Metadata-Version: 1.1
Name: sourpuss
Version: 0.3
Summary: Like feeding pickles to a cat(1)
Home-page: https://github.com/RhysU/sourpuss
Author: Rhys Ulerich
Author-email: rhys.ulerich@gmail.com
License: Mozilla Public License 2.0
Keywords: pandas cat pickle
Platform: UNKNOWN
Classifier: Development Status :: 3 - Alpha
Classifier: Environment :: Console
Classifier: Intended Audience :: Developers
Classifier: License :: OSI Approved :: Mozilla Public License 2.0 (MPL 2.0)
Classifier: Operating System :: OS Independent
Classifier: Programming Language :: Python :: 3 :: Only
Classifier: Topic :: Text Processing :: General
Classifier: Topic :: Utilities
